hydra_python_core/__init__.py
hydra_python_core/doc_maker.py
hydra_python_core/doc_writer.py
hydra_python_core/namespace.py
samples/__init__.py
samples/cli.py
samples/doc_writer_sample.py
samples/doc_writer_sample_output.py
samples/hydra_doc_sample.py
tests/__init__.py
tests/test_doc_maker.py
tests/test_doc_writer.py
tests/test_pep8.py
hydra_python_core-0.3.1.dist-info/LICENSE
hydra_python_core-0.3.1.dist-info/METADATA
hydra_python_core-0.3.1.dist-info/WHEEL
hydra_python_core-0.3.1.dist-info/top_level.txt
hydra_python_core-0.3.1.dist-info/RECORD
