Metadata-Version: 2.1
Name: hydra-python-core
Version: 0.3.1
Summary: Core functions for Hydrus
Home-page: https://github.com/HTTP-APIs/hydra-python-core
Author: Hydra Ecosystem
Author-email: collective@hydraecosystem.org
License: MIT
Platform: UNKNOWN
License-File: LICENSE
Requires-Dist: requests
Requires-Dist: sphinx (==3.1.2)
